gh_feed/__init__.py
gh_feed/app.py
gh_feed-0.1.8.dist-info/licenses/LICENSE
gh_feed-0.1.8.dist-info/METADATA
gh_feed-0.1.8.dist-info/WHEEL
gh_feed-0.1.8.dist-info/entry_points.txt
gh_feed-0.1.8.dist-info/top_level.txt
gh_feed-0.1.8.dist-info/RECORD
