Metadata-Version: 2.4
Name: gh-feed
Version: 0.1.8
Summary: A CLI tool to fetch and display GitHub user activity.
Author-email: Hamza Danjaji <bhantsi@gmail.com>
License: MIT License
Project-URL: Homepage, https://github.com/bhantsi/gh-feed
Project-URL: Repository, https://github.com/bhantsi/gh-feed
Project-URL: Issues, https://github.com/bhantsi/gh-feed/issues
Project-URL: Documentation, https://github.com/bhantsi/gh-feed#readme
Classifier: Programming Language :: Python :: 3
Classifier: Programming Language :: Python :: 3.7
Classifier: Programming Language :: Python :: 3.8
Classifier: Programming Language :: Python :: 3.9
Classifier: Programming Language :: Python :: 3.10
Classifier: Programming Language :: Python :: 3.11
Classifier: Programming Language :: Python :: 3.12
Classifier: License :: OSI Approved :: MIT License
Classifier: Operating System :: OS Independent
Classifier: Intended Audience :: Developers
Classifier: Topic :: Software Development :: Libraries :: Application Frameworks
Classifier: Topic :: Utilities
Requires-Python: >=3.7
License-File: LICENSE
Dynamic: license-file
